LICENSE.txt
README.md
pyproject.toml
src/pyrebel/__init__.py
src/pyrebel/abstract.py
src/pyrebel/edge.py
src/pyrebel/getnonzeros.py
src/pyrebel/learn.py
src/pyrebel/preprocess.py
src/pyrebel/utils.py
src/pyrebel.egg-info/PKG-INFO
src/pyrebel.egg-info/SOURCES.txt
src/pyrebel.egg-info/dependency_links.txt
src/pyrebel.egg-info/requires.txt
src/pyrebel.egg-info/top_level.txt