Metadata-Version: 2.4
Name: pyrebel
Version: 1.2.1
Summary: A pure python library that implements abstraction of data.
Author-email: Nithin PS <nithin.pulpra@gmail.com>
Maintainer-email: Nithin PS <nithin.pulpra@gmail.com>
License:                     GNU GENERAL PUBLIC LICENSE
Project-URL: Homepage, https://github.com/ps-nithin/pyrebel
Project-URL: Repository, https://github.com/ps-nithin/pyrebel
Keywords: data,abstraction,vision,machinelearning,patternrecognition,imagerecognition
Classifier: Development Status :: 4 - Beta
Classifier: Programming Language :: Python
Classifier: Environment :: GPU :: NVIDIA CUDA
Classifier: License :: OSI Approved :: GNU General Public License v3 (GPLv3)
Classifier: Intended Audience :: Science/Research
Classifier: Intended Audience :: Developers
Classifier: Intended Audience :: Education
Classifier: Topic :: Software Development
Classifier: Topic :: Scientific/Engineering
Classifier: Natural Language :: English
Requires-Python: >=3.8
License-File: LICENSE.txt
Requires-Dist: numpy
Requires-Dist: numba
Requires-Dist: Pillow
Dynamic: license-file
